<?xml version="1.0" encoding="UTF-8"?>
<odoo>
    <data>
        <record id="edit_view_hr_payslip_form_for_total" model="ir.ui.view">
            <field name="name">hr.payslip.form</field>
            <field name="model">hr.payslip</field>
            <field name="inherit_id" ref="hr_payroll.view_hr_payslip_form"/>
            <field name="arch" type="xml">
                <xpath expr="//field[@name='contract_id']" position="after">
                    <field name="resignation_id"/>
                </xpath>
            </field>
        </record>
    </data>
</odoo>